{
    "behavior": "", 
    "checkable": false, 
    "class": "div", 
    "clickable": false, 
    "content-desc": "", 
    "enabled": false, 
    "focusable": false, 
    "focused": false, 
    "hash": "oDGHH1xy3ToUJIuBroxhUQ==\n", 
    "height": 65, 
    "hier_level": 0, 
    "human_hash": "div_X20_Y711_W300_H65", 
    "human_readable": "div_20_711_300_65_div_7fff00000fff1fff1fff1fff1dff1c0e1c0e9cdf1fff1fff1fff1fff00006000_70391f674d70bf6a1fbb3407a83b113e", 
    "image_path": "M2M5MjZjNTAyOTA1ODU1ZGM3ODI0YTM4ZTk1MmUxZDQ.png", 
    "index": -1, 
    "internal": {
        "elem_dict": {
            "attributes": {
                "class": "flex row border top md bg"
            }, 
            "background-color": "rgba(0, 0, 0, 0)", 
            "class": "div", 
            "color": "rgb(26, 32, 44)", 
            "cssClass": "flex row border top md bg", 
            "domLevel": 8, 
            "flags": {
                "checkable": false, 
                "clickable": false, 
                "enabled": false, 
                "focusable": false, 
                "focused": false, 
                "scrollable": false
            }, 
            "font-family": "\"IBM Plex Sans\", sans-serif", 
            "font-weight": "400", 
            "fontSize": 13, 
            "height": 65, 
            "identifier": "", 
            "is-focused": false, 
            "is-hidden": false, 
            "name": "", 
            "tagName": "div", 
            "text": "6\u00a0 Wait for LabelLabelsDrag and dropContinue on failureType labels above or drag and drop an element or screen here to use its labelsDescriptionWait Timeout", 
            "type": "", 
            "value": "", 
            "width": 300, 
            "x": 20, 
            "xPercent": 1.0416666666666665, 
            "y": 711, 
            "yPercent": 25.71428571428571
        }, 
        "location": {
            "x": 20, 
            "y": 711
        }, 
        "size": {
            "height": 65, 
            "width": 300
        }, 
        "tag_name": "div", 
        "text": "6\u00a0 Wait for LabelLabelsDrag and dropContinue on failureType labels above or drag and drop an element or screen here to use its labelsDescriptionWait Timeout"
    }, 
    "is_transformed": true, 
    "package": "", 
    "password": false, 
    "resource-id": "", 
    "screen_hash": "5b76b116a43930bc8ce30b215060a868", 
    "scrollable": false, 
    "tag_name": "div", 
    "text": "6\u00a0 Wait for LabelLabelsDrag and dropContinue on failureType labels above or drag and drop an element or screen here to use its labelsDescriptionWait Timeout", 
    "transformed": true, 
    "width": 300, 
    "x": 20, 
    "y": 711
}